pyproject_aliases/__init__.py
pyproject_aliases/main.py
pyproject_aliases-0.2.0.dist-info/METADATA
pyproject_aliases-0.2.0.dist-info/WHEEL
pyproject_aliases-0.2.0.dist-info/entry_points.txt
pyproject_aliases-0.2.0.dist-info/RECORD
