Metadata-Version: 2.4
Name: pyproject_aliases
Version: 0.2.0
Summary: A simple tool to manage aliases in pyproject.toml
Project-URL: Homepage, https://github.com/tkk2112/pyproject_aliases
Project-URL: Issues, https://github.com/tkk2112/pyproject_aliases/issues
Project-URL: Repository, https://github.com/tkk2112/pyproject_aliases.git
Author-email: Thomas Kristensen <thomas@sl.m04r.space>
License-Expression: MIT
Requires-Python: >=3.11
